msorm/__init__.py
msorm/__main__.py
msorm/exceptions.py
msorm/extras.py
msorm/main.py
msorm/models.py
msorm/mssql_fields.py
msorm/operators.py
msorm/settings.py
msorm/type_fields.py
msorm-1.7.1a0.dist-info/LICENSE
msorm-1.7.1a0.dist-info/METADATA
msorm-1.7.1a0.dist-info/WHEEL
msorm-1.7.1a0.dist-info/top_level.txt
msorm-1.7.1a0.dist-info/RECORD
