Metadata-Version: 2.1
Name: msorm
Version: 1.7.1a0
Summary: ORM support for Mssql in python3
Home-page: https://github.com/bilinenkisi/msorm
Author: Mehmet Berkay Özbay
Author-email: <berkayozbay64@gmail.com>
License: UNKNOWN
Keywords: python,MSORM,msorm,mssql-python,mssql orm in python
Platform: UNKNOWN
Classifier: Development Status :: 3 - Alpha
Classifier: Programming Language :: Python :: 3
Classifier: Programming Language :: Python :: 3.7
Classifier: Operating System :: MacOS :: MacOS X
Classifier: Operating System :: Microsoft :: Windows
License-File: LICENSE
Requires-Dist: pyodbc
Requires-Dist: tqdm
